{
  "requestsFinished": 3,
  "requestsFailed": 0,
  "requestsRetries": 0,
  "requestsFailedPerMinute": 0,
  "requestsFinishedPerMinute": 0,
  "requestMinDurationMillis": 46155,
  "requestMaxDurationMillis": 67319,
  "requestTotalFailedDurationMillis": 0,
  "requestTotalFinishedDurationMillis": 169443,
  "crawlerStartedAt": "2024-10-11T14:56:40.341Z",
  "crawlerFinishedAt": null,
  "statsPersistedAt": "2024-10-11T15:03:51.789Z",
  "crawlerRuntimeMillis": 432324,
  "crawlerLastStartTimestamp": 1728658599465,
  "requestRetryHistogram": [
    3
  ],
  "statsId": 0,
  "requestAvgFailedDurationMillis": null,
  "requestAvgFinishedDurationMillis": 56481,
  "requestTotalDurationMillis": 169443,
  "requestsTotal": 3,
  "requestsWithStatusCode": {
    "200": 29
  },
  "errors": {},
  "retryErrors": {
    "C:\\Users\\Moon Computers\\Desktop\\web-scrapper\\node_modules\\@apify\\src\\index.ts:88:74": {
      "missing error code": {
        "Error": {
          "requestHandler timed out after 60 seconds.": {
            "count": 26
          }
        }
      }
    },
    "C:\\Users\\Moon Computers\\Desktop\\web-scrapper\\node_modules\\@crawlee\\src\\internals\\utils\\playwright-utils.ts:231:17": {
      "missing error code": {
        "Error": {
          "page.goto: net::ERR_EMPTY_RESPONSE at _": {
            "count": 4
          },
          "page.goto: net::ERR_CERT_AUTHORITY_INVALID at _": {
            "count": 4
          },
          "page.goto: net::ERR_CONNECTION_RESET at _": {
            "count": 37
          }
        }
      }
    }
  }
}