{
	"id": "rylRs88K3euNb8J",
	"json": "{\"id\":\"rylRs88K3euNb8J\",\"url\":\"https://www.copyrightable.com/search/registrations?q=photographs&page=238\",\"loadedUrl\":\"https://www.copyrightable.com/search/registrations?q=photographs&page=238\",\"uniqueKey\":\"https://www.copyrightable.com/search/registrations?page=238&q=photographs\",\"method\":\"GET\",\"noRetry\":false,\"retryCount\":0,\"errorMessages\":[],\"headers\":{},\"userData\":{\"__crawlee\":{\"state\":4}},\"handledAt\":\"2024-11-05T14:04:20.652Z\"}",
	"method": "GET",
	"orderNo": null,
	"retryCount": 0,
	"uniqueKey": "https://www.copyrightable.com/search/registrations?page=238&q=photographs",
	"url": "https://www.copyrightable.com/search/registrations?q=photographs&page=238"
}