{
	"id": "UixLnedfKOpLNRN",
	"json": "{\"id\":\"UixLnedfKOpLNRN\",\"url\":\"https://www.copyrightable.com/search/registrations?q=photographs&page=176\",\"loadedUrl\":\"https://www.copyrightable.com/search/registrations?q=photographs&page=176\",\"uniqueKey\":\"https://www.copyrightable.com/search/registrations?page=176&q=photographs\",\"method\":\"GET\",\"noRetry\":false,\"retryCount\":0,\"errorMessages\":[],\"headers\":{},\"userData\":{\"__crawlee\":{\"state\":4}},\"handledAt\":\"2024-11-05T14:03:08.296Z\"}",
	"method": "GET",
	"orderNo": null,
	"retryCount": 0,
	"uniqueKey": "https://www.copyrightable.com/search/registrations?page=176&q=photographs",
	"url": "https://www.copyrightable.com/search/registrations?q=photographs&page=176"
}